{
  "root": true,
  "ignorePatterns": ["**/*"],
  "overrides": [
    {
      "files": ["*.ts", "*.tsx", "*.js", "*.jsx"],
      "rules": {}
    },
    {
      "files": ["*.ts", "*.tsx"],
      "extends": ["plugin:@typescript-eslint/recommended"],
      "plugins": ["unused-imports"],
      "rules": {
        "unused-imports/no-unused-imports": "warn",
        "@typescript-eslint/no-unused-vars": [
          "warn",
          {
            "varsIgnorePattern": "^_",
            "argsIgnorePattern": "^_"
          }
        ],
        "@typescript-eslint/no-explicit-any": "warn"
      }
    },
    {
      "files": ["*.js", "*.jsx"],
      "rules": {}
    }
  ]
}
